<?xml version="1.0" encoding="UTF-8"?>
<NativeDicomModel xml-space="preserved">
	<DicomAttribute keyword="PatientID" tag="00100020" vr="LO">
		<Value number="1">P-000001</Value>
	</DicomAttribute>
	<DicomAttribute keyword="StudyInstanceUID" tag="0020000D" vr="UI">
		<Value number="1">1.2.40.0.13.1.15.110.3.9999.1</Value>
	</DicomAttribute>
	<DicomAttribute keyword="SeriesInstanceUID" tag="0020000E" vr="UI">
		<Value number="1">1.2.40.0.13.1.15.110.3.9999.2</Value>
	</DicomAttribute>
</NativeDicomModel>
